[{"id":500352002,"ko":"마도서 (미티어)","jp":"魔導書(メテオ)","ru":"Книга Магии (Метеор)","tw":"","icon":"Item_Usable_SkillBook_Staff_05.png","normal":["0,0.6459%,13-5","0,0.6459%,14-5","0,0.6459%,15-4","0,0.6459%,16-4","0,0.6459%,17-3","0,0.6459%,18-3","0,0.6459%,19-2","0,0.6459%,20-2","0,0.6459%,21-1","0,0.6459%,22-1"],"top":["0,0.8869%,13-5","0,0.8869%,14-4","0,0.8869%,16-3","0,0.8869%,18-3","0,0.8869%,19-2"]},{"id":500352004,"ko":"마도서 (카오스)","jp":"魔導書(カオス)","ru":"Книга Магии (Хаос)","tw":"","icon":"Item_Usable_SkillBook_Staff_05.png","normal":["0,0.6459%,13-5","0,0.6459%,14-5","0,0.6459%,15-4","0,0.6459%,16-4","0,0.6459%,17-3","0,0.6459%,18-3","0,0.6459%,19-2","0,0.6459%,20-2","0,0.6459%,21-1","0,0.6459%,22-1"],"top":["0,0.8869%,13-5","0,0.8869%,14-4","0,0.8869%,16-3","0,0.8869%,18-3","0,0.8869%,19-2"]},{"id":500352005,"ko":"마도서 (그라비티)","jp":"魔導書(グラビティ)","ru":"Книга Магии (Гравитация)","tw":"","icon":"Item_Usable_SkillBook_Staff_05.png","normal":["0,0.6459%,13-5","0,0.6459%,14-5","0,0.6459%,15-4","0,0.6459%,16-4","0,0.6459%,17-3","0,0.6459%,18-3","0,0.6459%,19-2","0,0.6459%,20-2","0,0.6459%,21-1","0,0.6459%,22-1"],"top":["0,0.8869%,13-5","0,0.8869%,14-4","0,0.8869%,16-3","0,0.8869%,18-3","0,0.8869%,19-2"]},{"id":500352006,"ko":"마도서 (스티그마)","jp":"魔導書(スティグマ)","ru":"Книга Магии (Стигма)","tw":"","icon":"Item_Usable_SkillBook_Staff_05.png","normal":["0,0.6459%,13-5","0,0.6459%,14-5","0,0.6459%,15-4","0,0.6459%,16-4","0,0.6459%,17-3","0,0.6459%,18-3","0,0.6459%,19-2","0,0.6459%,20-2","0,0.6459%,21-1","0,0.6459%,22-1"],"top":["0,0.8869%,13-5","0,0.8869%,14-4","0,0.8869%,16-3","0,0.8869%,18-3","0,0.8869%,19-2"]},{"id":500352008,"ko":"마도서 (글래시어 스톰)","jp":"魔導書(グレイシャーストーム)","ru":"Книга Магии (Ледяной Шторм)","tw":"","icon":"Item_Usable_SkillBook_Staff_05.png","top":["0,2.0661%,15-5","0,2.0661%,16-4","0,2.0661%,17-4","0,2.0661%,18-4","0,2.0661%,19-4"]},{"id":500353001,"ko":"마도서 (블리자드 스톰)","jp":"魔導書(ブリザードストーム)","ru":"Книга Магии (Снежный Шторм)","tw":"","icon":"Item_Usable_SkillBook_Staff_04.png","normal":["0,0.7623%,5-5","0,0.7623%,6-4","0,0.7623%,8-3","0,0.7623%,10-2","0,0.7623%,12-1"],"top":["0,0.9267%,4-5","0,0.9267%,9-2","0,0.9267%,11-1"]},{"id":500353002,"ko":"마도서 (캔슬)","jp":"魔導書(キャンセル)","ru":"Книга Магии (Отмена)","tw":"","icon":"Item_Usable_SkillBook_Staff_04.png","normal":["0,0.5197%,7-5","0,0.5197%,8-4","0,0.5197%,10-3","0,0.5197%,12-2","0,0.5197%,14-1"],"top":["0,0.3880%,5-5","0,0.3880%,6-4","0,0.3880%,8-3","0,0.3880%,10-2","0,0.3880%,12-1"]},{"id":500353004,"ko":"마도서 (리스토어 캐스팅)","jp":"魔導書(リストアキャスティングⅠ)","ru":"Книга Магии (Восстановление Заклинаний Ⅰ)","tw":"","icon":"Item_Usable_SkillBook_Staff_04.png","normal":["0,0.7623%,5-5","0,0.7623%,6-4","0,0.7623%,8-3","0,0.7623%,10-2","0,0.7623%,12-1"],"top":["0,0.9267%,4-5","0,0.9267%,9-2","0,0.9267%,11-1"]},{"id":500353005,"ko":"마도서 (컨퓨즈)","jp":"魔導書(コンフューズ)","ru":"Книга Магии (Замешательство)","tw":"","icon":"Item_Usable_SkillBook_Staff_04.png","normal":["0,0.7623%,5-5","0,0.7623%,6-4","0,0.7623%,8-3","0,0.7623%,10-2","0,0.7623%,12-1"],"top":["0,0.9267%,4-5","0,0.9267%,9-2","0,0.9267%,11-1"]},{"id":500353006,"ko":"마도서 (아케인 파워)","jp":"魔導書(アルケインパワー)","ru":"Книга Магии (Тайная Мощь)","tw":"","icon":"Item_Usable_SkillBook_Staff_04.png","normal":["0,0.6202%,4-5","0,0.6202%,5-4","0,0.6202%,7-3","0,0.6202%,9-2","0,0.6202%,10-1","0,0.6202%,11-1"]},{"id":500353008,"ko":"마도서 (프로즌 크리스탈)","jp":"魔導書(フローズンクリスタル)","ru":"Книга Магии (Кристалл Инея)","tw":"","icon":"Item_Usable_SkillBook_Staff_04.png","normal":["0,0.8850%,8-5","0,0.8850%,9-4","0,0.8850%,11-3","0,0.8850%,13-2","0,0.8850%,15-1"],"top":["0,1.1640%,7-5","0,1.1640%,8-4","0,1.1640%,10-3","0,1.1640%,12-2","0,1.1640%,14-1"]},{"id":500353009,"ko":"마도서 (데블스 웨이)","jp":"魔導書(テンペストⅢ)","ru":"Книга Магии (Буря Ⅲ)","tw":"","icon":"Item_Usable_SkillBook_Staff_04.png","normal":["0,0.8850%,8-5","0,0.8850%,9-4","0,0.8850%,11-3","0,0.8850%,13-2","0,0.8850%,15-1"],"top":["0,1.1640%,7-5","0,1.1640%,8-4","0,1.1640%,10-3","0,1.1640%,12-2","0,1.1640%,14-1"]},{"id":500354003,"ko":"마도서 (크리티컬 매직)","jp":"魔導書（クリティカルマジック）","ru":"Книга Магии (Критическая Магия)","tw":"","icon":"Item_Usable_SkillBook_Staff_03.png","normal":["0,0.0033%,1-1","0,0.0033%,2-1"]},{"id":500354004,"ko":"마도서 (엠파워 오브 에코)","jp":"魔導書(エンパワーオブエコー)","ru":"Книга Магии (Эхо Воодушевления)","tw":"","icon":"Item_Usable_SkillBook_Staff_03.png","normal":["0,0.0033%,1-1","0,0.0033%,2-1"]},{"id":500354005,"ko":"마도서 (배틀 힐)","jp":"魔導書(バトルヒール)","ru":"Книга Магии (Боевое Лечение)","tw":"","icon":"Item_Usable_SkillBook_Staff_03.png","normal":["0,0.0033%,1-1","0,0.0033%,2-1"]},{"id":500354006,"ko":"마도서 (마나 리제네레이션)","jp":"魔導書(マナ·リジェネレーション)","ru":"Книга Магии (Регенерация Маны)","tw":"","icon":"Item_Usable_SkillBook_Staff_03.png","normal":["0,0.5839%,2-2","0,0.5839%,4-1"],"top":["0,1.2557%,1-2","0,1.2557%,3-1"]},{"id":500354007,"ko":"마도서 (어스 보텍스)","jp":"魔導書(テンペストⅡ)","ru":"Книга Магии (Буря Ⅱ)","tw":"","icon":"Item_Usable_SkillBook_Staff_03.png","normal":["0,0.0033%,1-1","0,0.0033%,2-1"]},{"id":500354008,"ko":"마도서 (다크니스)","jp":"魔導書(ダークネス)","ru":"Книга Магии (Тьма)","tw":"","icon":"Item_Usable_SkillBook_Staff_03.png","normal":["0,0.0033%,1-1","0,0.0033%,2-1"]},{"id":500354009,"ko":"마도서 (클리어 마인드)","jp":"魔導書(クリアーマインド)","ru":"Книга Магии (Светлый Разум)","tw":"","icon":"Item_Usable_SkillBook_Staff_03.png","normal":["0,0.5839%,2-2","0,0.5839%,4-1"],"top":["0,1.2557%,1-2","0,1.2557%,3-1"]},{"id":500354010,"ko":"마도서 (콘센트레이션 스펠)","jp":"魔導書(コンセントレーションスペル)","ru":"Книга Магии (Заклинание Концентрации)","tw":"","icon":"Item_Usable_SkillBook_Staff_03.png","normal":["0,0.0033%,1-1","0,0.0033%,2-1"]},{"id":500355001,"ko":"마도서 (플레임 스트라이크)","jp":"魔導書(フレイムストライク)","ru":"Книга Магии (Удар Пламени)","tw":"","icon":"Item_Usable_SkillBook_Staff_02.png","normal":["0,0.0268%,1-1","0,0.0268%,2-1"]},{"id":500355002,"ko":"마도서 (매지션즈 무브먼트)","jp":"魔導書(マジシャンズムーブメント)","ru":"Книга Магии (Движение Мага)","tw":"","icon":"Item_Usable_SkillBook_Staff_02.png","normal":["0,0.0891%,1-1","0,0.0891%,2-1"]},{"id":500355003,"ko":"마도서 (윈드 스트라이크)","jp":"魔導書(ウインドストライク)","ru":"Книга Магии (Удар Ветра)","tw":"","icon":"Item_Usable_SkillBook_Staff_02.png","normal":["0,0.0891%,1-1","0,0.0891%,2-1"]},{"id":500355004,"ko":"마도서 (템페스트)","jp":"魔導書(テンペストⅠ)","ru":"Книга Магии (Буря Ⅰ)","tw":"","icon":"Item_Usable_SkillBook_Staff_02.png","normal":["0,0.0536%,1-1","0,0.0536%,2-1"]},{"id":500355005,"ko":"마도서 (바디 투 마인드)","jp":"魔導書(ボディ·トゥ·マインド)","ru":"Книга Магии (Самобичевание)","tw":"","icon":"Item_Usable_SkillBook_Staff_02.png","normal":["0,0.0536%,1-1","0,0.0536%,2-1"]},{"id":500355007,"ko":"마도서 (부스트 마나)","jp":"魔導書(ブーストマナ)","ru":"Книга Магии (Увеличение Маны)","tw":"","icon":"Item_Usable_SkillBook_Staff_02.png","normal":["0,0.0891%,1-1","0,0.0891%,2-1"]},{"id":500355008,"ko":"마도서 (미스틱 쉴드)","jp":"魔導書(ミスティックシールド)","ru":"Книга Магии (Щит Мистика)","tw":"","icon":"Item_Usable_SkillBook_Staff_02.png","normal":["0,0.0268%,1-1","0,0.0268%,2-1"]}]